{
  "node_modules/@sveltejs/kit/src/runtime/client/start.js": {
    "file": "_app/immutable/start-efbf7d9e.js",
    "src": "node_modules/@sveltejs/kit/src/runtime/client/start.js",
    "isEntry": true,
    "imports": [
      "_index-73907dad.js",
      "_singletons-3a6bd635.js"
    ],
    "dynamicImports": [
      ".svelte-kit/generated/nodes/0.js",
      ".svelte-kit/generated/nodes/1.js",
      ".svelte-kit/generated/nodes/2.js",
      ".svelte-kit/generated/nodes/3.js"
    ]
  },
  "src/routes/+layout.svelte": {
    "file": "_app/immutable/components/pages/_layout.svelte-43d7dcdf.js",
    "src": "src/routes/+layout.svelte",
    "isEntry": true,
    "imports": [
      "_index-73907dad.js"
    ],
    "css": [
      "_app/immutable/assets/_layout-839e2461.css"
    ]
  },
  "node_modules/@sveltejs/kit/src/runtime/components/error.svelte": {
    "file": "_app/immutable/components/error.svelte-311ab0ef.js",
    "src": "node_modules/@sveltejs/kit/src/runtime/components/error.svelte",
    "isEntry": true,
    "imports": [
      "_index-73907dad.js",
      "_singletons-3a6bd635.js"
    ]
  },
  "src/routes/+page.svelte": {
    "file": "_app/immutable/components/pages/_page.svelte-7b7cccf6.js",
    "src": "src/routes/+page.svelte",
    "isEntry": true,
    "imports": [
      "_index-73907dad.js",
      "_header-8559998f.js"
    ],
    "css": [
      "_app/immutable/assets/_page-b42e3e14.css"
    ]
  },
  "src/routes/modeManager/+page.svelte": {
    "file": "_app/immutable/components/pages/modeManager/_page.svelte-3a81d4dc.js",
    "src": "src/routes/modeManager/+page.svelte",
    "isEntry": true,
    "imports": [
      "_index-73907dad.js",
      "_header-8559998f.js"
    ],
    "css": [
      "_app/immutable/assets/_page-b42e3e14.css"
    ]
  },
  "src/routes/+layout.js": {
    "file": "_app/immutable/modules/pages/_layout.js-5da876cb.js",
    "src": "src/routes/+layout.js",
    "isEntry": true,
    "imports": [
      "__layout-e6a1d6ec.js"
    ]
  },
  "_singletons-3a6bd635.js": {
    "file": "_app/immutable/chunks/singletons-3a6bd635.js",
    "imports": [
      "_index-73907dad.js"
    ]
  },
  "_index-73907dad.js": {
    "file": "_app/immutable/chunks/index-73907dad.js"
  },
  "__layout-e6a1d6ec.js": {
    "file": "_app/immutable/chunks/_layout-e6a1d6ec.js"
  },
  "_header-8559998f.js": {
    "file": "_app/immutable/chunks/header-8559998f.js",
    "imports": [
      "_index-73907dad.js"
    ],
    "css": [
      "_app/immutable/assets/header-9f424162.css"
    ]
  },
  ".svelte-kit/generated/nodes/0.js": {
    "file": "_app/immutable/chunks/0-051ad95f.js",
    "src": ".svelte-kit/generated/nodes/0.js",
    "isDynamicEntry": true,
    "imports": [
      "__layout-e6a1d6ec.js",
      "src/routes/+layout.svelte"
    ]
  },
  ".svelte-kit/generated/nodes/1.js": {
    "file": "_app/immutable/chunks/1-876142b6.js",
    "src": ".svelte-kit/generated/nodes/1.js",
    "isDynamicEntry": true,
    "imports": [
      "node_modules/@sveltejs/kit/src/runtime/components/error.svelte"
    ]
  },
  ".svelte-kit/generated/nodes/2.js": {
    "file": "_app/immutable/chunks/2-8ed007f3.js",
    "src": ".svelte-kit/generated/nodes/2.js",
    "isDynamicEntry": true,
    "imports": [
      "src/routes/+page.svelte"
    ]
  },
  ".svelte-kit/generated/nodes/3.js": {
    "file": "_app/immutable/chunks/3-ab8ffb89.js",
    "src": ".svelte-kit/generated/nodes/3.js",
    "isDynamicEntry": true,
    "imports": [
      "src/routes/modeManager/+page.svelte"
    ]
  },
  "src/routes/modeManager/+page.css": {
    "file": "_app/immutable/assets/_page-b42e3e14.css",
    "src": "src/routes/modeManager/+page.css"
  },
  "header.css": {
    "file": "_app/immutable/assets/header-9f424162.css",
    "src": "header.css"
  },
  "src/routes/+layout.css": {
    "file": "_app/immutable/assets/_layout-839e2461.css",
    "src": "src/routes/+layout.css"
  }
}